{
  "attractions": [
    {
      "id": "nuo-1771587704099",
      "name": "万固寺",
      "slogan": "中条第一禅林",
      "short_review": "✍️ 记录于: 2026/2/20\n\n\u3000\u3000主塔多宝佛塔塔身雄伟，颇有历史感，寺庙整体盘山而建，环境清幽，佛教氛围浓厚。\n\n\u3000\u3000有故事、有传承，虽然没到“热泪盈眶”的地步，但确实不虚此行——被誉为“中条第一禅林”。\n\n\u3000\u3000来的时候正在修路，门口山路又陡又长，爬的有点累。\n\n\u3000\u3000 景点我去的时候是免费的，很值得推荐。",
      "images": [
        "/rate/rateimg/wgs1.jpg",
        "/rate/rateimg/wgs2.jpg",
        "/rate/rateimg/wgs3.jpg"
      ],
      "location": "山西省运城市永济市蒲州镇",
      "visit_time": "2026.2.19",
      "scores": {
        "architecture": { "text": "8", "val": 8 },
        "culture": { "text": "8-", "val": 7.8 },
        "experience": { "text": "6.5-", "val": 6.3 },
        "value": { "text": "10", "val": 10 }
      },
      "tags": [ { "name": "免费", "tier": "B" } ],
      "final_score": 8.02,
      "rating": "A-"
    },
    {
      "id": "guanquelou",
      "name": "鹳雀楼",
      "slogan": "白日依山尽，黄河入海流。",
      "short_review": "✍️ 记录于: 2026.2.19\n\n\u3000\u3000现代重修，内部甚至还有电梯，内部装修现代化，没有那种古代的震撼感，但是楼修的很宏伟，周围一望无际，长河落日，视觉冲击力强。\n\n\u3000\u3000登高望远，天地辽阔，一望无极，顿与斯人同感，白日依山尽，黄河入海流。欲穷千里目，更上一层楼！跨越千年，虽世殊事异，所以兴怀，其致一也。\n\n\u3000\u3000 楼内有电梯，排队也没有很久。进大门到鹳雀楼部分有点远，路边是商业摆摊、文创店等。上楼先要爬台阶。\n\n\u3000\u3000 门票50元，主要项目是爬楼登高望远，体会耳熟能详的登鹳雀楼情感。",
      "images": [
        "/rate/rateimg/gql1.jpg",
        "/rate/rateimg/gql2.jpg"
      ],
      "location": "山西省运城市永济市蒲州镇",
      "visit_time": "2026.2.18",
      "scores": {
        "architecture": { "text": "6.5-", "val": 6.3 },
        "culture": { "text": "8.5", "val": 8.5 },
        "experience": { "text": "7.5+", "val": 7.7 },
        "value": { "text": "7", "val": 6.8 }
      },
      "tags": [ { "name": "欲穷千里目", "tier": "S" } ],
      "final_score": 7.75,
      "rating": "B+"
    }
  ]
}